odoo/addons/edi_sale_ubl_output_oca/README.rst
odoo/addons/edi_sale_ubl_output_oca/__init__.py
odoo/addons/edi_sale_ubl_output_oca/__manifest__.py
odoo/addons/edi_sale_ubl_output_oca/demo/edi_exchange_type.xml
odoo/addons/edi_sale_ubl_output_oca/demo/exc_templ_order_response.xml
odoo/addons/edi_sale_ubl_output_oca/i18n/edi_sale_ubl_output_oca.pot
odoo/addons/edi_sale_ubl_output_oca/i18n/it.po
odoo/addons/edi_sale_ubl_output_oca/readme/CONTRIBUTORS.md
odoo/addons/edi_sale_ubl_output_oca/readme/DESCRIPTION.md
odoo/addons/edi_sale_ubl_output_oca/static/description/icon.png
odoo/addons/edi_sale_ubl_output_oca/static/description/index.html
odoo/addons/edi_sale_ubl_output_oca/templates/qweb_tmpl_order_response.xml
odoo/addons/edi_sale_ubl_output_oca/templates/qweb_tmpl_party.xml
odoo/addons/edi_sale_ubl_output_oca/tests/__init__.py
odoo/addons/edi_sale_ubl_output_oca/tests/test_order_in_full_flow.py
odoo/addons/edi_sale_ubl_output_oca/tests/test_order_response_out.py
odoo_addon_edi_sale_ubl_output_oca-18.0.1.0.1.dist-info/METADATA
odoo_addon_edi_sale_ubl_output_oca-18.0.1.0.1.dist-info/WHEEL
odoo_addon_edi_sale_ubl_output_oca-18.0.1.0.1.dist-info/top_level.txt
odoo_addon_edi_sale_ubl_output_oca-18.0.1.0.1.dist-info/RECORD
